AUTHOR.txt
CHANGES.txt
LICENSE.txt
buildout.cfg
setup.py
bootstrap/bootstrap.py
src/falkolab/__init__.py
src/falkolab.recipe.csstools.egg-info/PKG-INFO
src/falkolab.recipe.csstools.egg-info/SOURCES.txt
src/falkolab.recipe.csstools.egg-info/dependency_links.txt
src/falkolab.recipe.csstools.egg-info/entry_points.txt
src/falkolab.recipe.csstools.egg-info/namespace_packages.txt
src/falkolab.recipe.csstools.egg-info/not-zip-safe
src/falkolab.recipe.csstools.egg-info/requires.txt
src/falkolab.recipe.csstools.egg-info/top_level.txt
src/falkolab/recipe/__init__.py
src/falkolab/recipe/csstools/README.txt
src/falkolab/recipe/csstools/__init__.py
src/falkolab/recipe/csstools/builder.py
src/falkolab/recipe/csstools/combiner.py