Metadata-Version: 1.0
Name: falkolab.recipe.csstools
Version: 1.0.2
Summary: CSS tools recipe for buildout
Home-page: UNKNOWN
Author: Andrey Tkachenko
Author-email: falko.lab@gmail.com
License: ZPL 2.1
Platform: UNKNOWN
Classifier: Development Status :: 5 - Production/Stable
Classifier: Environment :: Web Environment
Classifier: Intended Audience :: Developers
Classifier: License :: OSI Approved :: Zope Public License
Classifier: Programming Language :: Python
Classifier: Natural Language :: English
Classifier: Operating System :: OS Independent
Classifier: Topic :: Software Development :: Build Tools
